{
   "content" : {
      "begin" : "0",
      "end" : "475",
      "filename" : "content.bin",
      "part" : [
         {
            "begin" : "172",
            "end" : "339",
            "type" : "pdp8/unknown"
         }
      ]
   },
   "description" : [
      "Basic PDP8, 8I Memory Checkerboard (High)"
   ],
   "label" : "MAINDEC-08-D1L2-PM",
   "source" : {
      "email" : "hachti@hachti.de",
      "name" : "Philipp Hachtmann",
      "url" : "http://pdp8.hachti.de/pdp8l/software/"
   }
}
